tum_esm_utils-2.11.4.dist-info/METADATA
tum_esm_utils-2.11.4.dist-info/WHEEL
tum_esm_utils-2.11.4.dist-info/entry_points.txt
tum_esm_utils-2.11.4.dist-info/licenses/LICENSE
tum_esm_utils/__init__.py
tum_esm_utils/code.py
tum_esm_utils/column/.gitignore
tum_esm_utils/column/__init__.py
tum_esm_utils/column/astronomy.py
tum_esm_utils/column/averaging_kernel.py
tum_esm_utils/column/ncep_profiles.py
tum_esm_utils/dataframes.py
tum_esm_utils/datastructures.py
tum_esm_utils/decorators.py
tum_esm_utils/em27.py
tum_esm_utils/files.py
tum_esm_utils/mathematics.py
tum_esm_utils/netcdf.py
tum_esm_utils/opus/__init__.py
tum_esm_utils/opus/file_interface.py
tum_esm_utils/opus/http_interface.py
tum_esm_utils/opus/types.py
tum_esm_utils/opus/utils.py
tum_esm_utils/opus_file_validator/.gitignore
tum_esm_utils/opus_file_validator/glob_OPUSparms6.F90
tum_esm_utils/opus_file_validator/glob_prepro6.F90
tum_esm_utils/opus_file_validator/opus_file_validator.F90
tum_esm_utils/opus_file_validator/opus_file_validator.template.inp
tum_esm_utils/opus_file_validator/refspec.dat
tum_esm_utils/opus_file_validator/refspec2.dat
tum_esm_utils/plotting.py
tum_esm_utils/processes.py
tum_esm_utils/py.typed
tum_esm_utils/rebinning.py
tum_esm_utils/shell.py
tum_esm_utils/sqlitelock.py
tum_esm_utils/system.py
tum_esm_utils/text.py
tum_esm_utils/timing.py
tum_esm_utils/validators.py
tum_esm_utils-2.11.4.dist-info/RECORD
