Metadata-Version: 2.1
Name: tum_esm_utils
Version: 2.11.4
Summary: Python utilities by the Professorship of Environmental Sensing and Modeling at the Technical University of Munich
Keywords: tum,utils,utilities,environmental,sensing,modeling,python,library,pydoc-markdown
Author-Email: Moritz Oliveira Makowski <moritz.makowski@tum.de>, Friedrich Klappenbach <friedrich.klappenbach@tum.de>
License: GPL-3.0-or-later
Classifier: License :: OSI Approved :: GNU General Public License (GPL)
Classifier: Programming Language :: Python :: 3
Classifier: Programming Language :: Python :: 3.10
Classifier: Programming Language :: Python :: 3.11
Classifier: Programming Language :: Python :: 3.12
Classifier: Programming Language :: Python :: 3.13
Classifier: Programming Language :: Python :: 3.14
Project-URL: repository, https://github.com/tum-esm/utils
Project-URL: documentation, https://tum-esm-utils.netlify.app
Requires-Python: <4.0,>=3.10
Requires-Dist: filelock>=3.18.0
Requires-Dist: requests>=2.32.5
Requires-Dist: psutil>=7.1.2
Requires-Dist: pydantic>=2.11.3
Requires-Dist: pytz>=2025.2
Requires-Dist: tailwind-colors>=1.3.0
Provides-Extra: dev
Requires-Dist: pytest>=8.3.5; extra == "dev"
Requires-Dist: pydocstyle>=6.3.0; extra == "dev"
Requires-Dist: mypy>=1.15.0; extra == "dev"
Requires-Dist: pydoc-markdown>=4.8.2; extra == "dev"
Requires-Dist: types-psutil>=7.0.0.20251001; extra == "dev"
Requires-Dist: types-requests>=2.32.0.20250328; extra == "dev"
Requires-Dist: types-pytz>=2025.2.0.20250326; extra == "dev"
Requires-Dist: ruff>=0.11.6; extra == "dev"
Requires-Dist: pytest-order>=1.3.0; extra == "dev"
Requires-Dist: scipy-stubs>=1.15.2.2; extra == "dev"
Requires-Dist: pyright>=1.1.407; extra == "dev"
Provides-Extra: plotting
Requires-Dist: matplotlib>=3.10.7; extra == "plotting"
Requires-Dist: numpy>=2.2.5; extra == "plotting"
Provides-Extra: em27
Requires-Dist: polars>=1.16.0; extra == "em27"
Provides-Extra: polars
Requires-Dist: polars>=1.16.0; extra == "polars"
Provides-Extra: opus
Requires-Dist: numpy>=2.2.5; extra == "opus"
Requires-Dist: tenacity>=9.1.2; extra == "opus"
Provides-Extra: modeling
Requires-Dist: polars>=1.16.0; extra == "modeling"
Requires-Dist: scipy>=1.15.2; extra == "modeling"
Requires-Dist: skyfield>=1.53; extra == "modeling"
Requires-Dist: numpy>=2.2.6; extra == "modeling"
Provides-Extra: netcdf
Requires-Dist: netcdf4>=1.7.3; extra == "netcdf"
Provides-Extra: all
Requires-Dist: matplotlib>=3.10.1; extra == "all"
Requires-Dist: numpy>=2.2.5; extra == "all"
Requires-Dist: polars>=1.16.0; extra == "all"
Requires-Dist: tenacity>=9.1.2; extra == "all"
Requires-Dist: scipy>=1.15.2; extra == "all"
Requires-Dist: skyfield>=1.53; extra == "all"
Requires-Dist: netcdf4>=1.7.3; extra == "all"
